odoo/addons/auth_saml/README.rst
odoo/addons/auth_saml/__init__.py
odoo/addons/auth_saml/__manifest__.py
odoo/addons/auth_saml/controllers/__init__.py
odoo/addons/auth_saml/controllers/main.py
odoo/addons/auth_saml/data/ir_config_parameter.xml
odoo/addons/auth_saml/i18n/auth_saml.pot
odoo/addons/auth_saml/i18n/es.po
odoo/addons/auth_saml/i18n/fr.po
odoo/addons/auth_saml/i18n/it.po
odoo/addons/auth_saml/models/__init__.py
odoo/addons/auth_saml/models/auth_saml_attribute_mapping.py
odoo/addons/auth_saml/models/auth_saml_provider.py
odoo/addons/auth_saml/models/auth_saml_request.py
odoo/addons/auth_saml/models/ir_config_parameter.py
odoo/addons/auth_saml/models/res_config_settings.py
odoo/addons/auth_saml/models/res_users.py
odoo/addons/auth_saml/models/res_users_saml.py
odoo/addons/auth_saml/readme/CONFIGURE.md
odoo/addons/auth_saml/readme/CONTRIBUTORS.md
odoo/addons/auth_saml/readme/DESCRIPTION.md
odoo/addons/auth_saml/readme/HISTORY.md
odoo/addons/auth_saml/readme/INSTALL.md
odoo/addons/auth_saml/readme/ROADMAP.md
odoo/addons/auth_saml/readme/USAGE.md
odoo/addons/auth_saml/security/ir.model.access.csv
odoo/addons/auth_saml/static/description/icon.png
odoo/addons/auth_saml/static/description/index.html
odoo/addons/auth_saml/tests/__init__.py
odoo/addons/auth_saml/tests/fake_idp.py
odoo/addons/auth_saml/tests/test_models_saml_attribute_mapping.py
odoo/addons/auth_saml/tests/test_pysaml.py
odoo/addons/auth_saml/tests/data/cert_idp_expired.pem
odoo/addons/auth_saml/tests/data/idp.pem
odoo/addons/auth_saml/tests/data/key_idp_expired.pem
odoo/addons/auth_saml/tests/data/sp.key
odoo/addons/auth_saml/tests/data/sp.pem
odoo/addons/auth_saml/views/auth_saml.xml
odoo/addons/auth_saml/views/res_config_settings.xml
odoo/addons/auth_saml/views/res_users.xml
odoo_addon_auth_saml-18.0.1.1.0.2.dist-info/METADATA
odoo_addon_auth_saml-18.0.1.1.0.2.dist-info/WHEEL
odoo_addon_auth_saml-18.0.1.1.0.2.dist-info/top_level.txt
odoo_addon_auth_saml-18.0.1.1.0.2.dist-info/RECORD
