Metadata-Version: 2.1
Name: odoo-addon-auth_saml
Version: 18.0.1.1.0.2
Requires-Python: >=3.10
Requires-Dist: odoo==18.0.*
Requires-Dist: pysaml2
Summary: SAML2 Authentication
Home-page: https://github.com/OCA/server-auth
License: AGPL-3
Author: XCG Consulting, Odoo Community Association (OCA)
Author-email: support@odoo-community.org
Classifier: Programming Language :: Python
Classifier: Framework :: Odoo
Classifier: Framework :: Odoo :: 18.0
Classifier: License :: OSI Approved :: GNU Affero General Public License v3
Classifier: Development Status :: 4 - Beta
